imgaug2/__init__.py
imgaug2-0.0.1.dist-info/METADATA
imgaug2-0.0.1.dist-info/WHEEL
imgaug2-0.0.1.dist-info/top_level.txt
imgaug2-0.0.1.dist-info/RECORD
