Metadata-Version: 2.4
Name: imgaug2
Version: 0.0.1
Summary: Image augmentation library for machine learning
Author-email: Alfredo Sandoval <Alfredo.Sandoval@protonmail.com>
License: MIT
Classifier: Development Status :: 1 - Planning
Classifier: License :: OSI Approved :: MIT License
Classifier: Programming Language :: Python :: 3.10
Requires-Python: >=3.10
